apppy/queues/__init__.py
apppy/queues/asyncio.py
apppy/queues/asyncio_unit_test.py
apppy_queues-0.23.2.dist-info/METADATA
apppy_queues-0.23.2.dist-info/WHEEL
apppy_queues-0.23.2.dist-info/RECORD
