Metadata-Version: 2.4
Name: apppy-queues
Version: 0.23.2
Summary: Python definitions for async processing over a queue for server development
Project-URL: Homepage, https://github.com/spals/apppy
Author: Tim Kral
License: MIT
Classifier: License :: OSI Approved :: MIT License
Classifier: Programming Language :: Python :: 3
Requires-Python: >=3.11
Requires-Dist: fastapi-lifespan-manager==0.1.4
